HeidelTime/__init__.py
HeidelTime/de.unihd.dbs.heideltime.standalone.jar
python_heideltime_krypton-0.0.2.dist-info/LICENSE
python_heideltime_krypton-0.0.2.dist-info/METADATA
python_heideltime_krypton-0.0.2.dist-info/WHEEL
python_heideltime_krypton-0.0.2.dist-info/top_level.txt
python_heideltime_krypton-0.0.2.dist-info/RECORD
