Metadata-Version: 2.1
Name: python-heideltime-krypton
Version: 0.0.2
Summary: Python wrapper for Heideltime library.
Home-page: https://github.com/Vetted/python-heideltime
Author: Bharadwaj Srigiriraju
Author-email: krishna.bharadwaj6@gmail.com
License: UNKNOWN
Platform: UNKNOWN
Classifier: Programming Language :: Python :: 3
Classifier: License :: OSI Approved :: GNU General Public License v3 (GPLv3)
Classifier: Operating System :: OS Independent
Requires-Python: >=3.6
